Workbook
Name aporte: Planilha1!$C$18
Name dividendos: Planilha1!$C$22
Name patrimonio: Planilha1!$C$21
Name qtd_anos: Planilha1!$C$19
Name rendimento_carteira: Planilha1!$C$13
Name tx_mensal: Planilha1!$C$20

Sheet Planilha1
B11: Configurações
B12: Salário | C12: 4200
B13: Rendimento da Carteira | C13: 0.01
B14: Sugestão de Investimento | C14: =C12*30% -> 1260
B17: INVESTIMENTO MENSAL
B18: Quanto invetsir por mês? | C18: 500
B19: Por quantos anos? | C19: 5
B20: Taxa de rendimento mensal? | C20: 0.0108
B21: Patrimônio acumulado? | C21: =FV(tx_mensal,qtd_anos*12,aporte*-1) -> 41902.01
B22: Dividendos mensais? | C22: =patrimonio*rendimento_carteira -> 419.0201
A25: 2 | B25: CENÁRIOS | D25: Dividendo
A26: 5 | B26: Quanto em 2 anos? | C26: =FV($C$13,$A25*12,$C$18*-1) -> 13486.732 | D26: =C26*rendimento_carteira -> 134.86732
A27: 10 | B27: Quanto em 5 anos? | C27: =FV($C$13,$A26*12,$C$18*-1) -> 40834.835 | D27: =C27*rendimento_carteira -> 408.34835
A28: 20 | B28: Quanto em 10 anos? | C28: =FV($C$13,$A27*12,$C$18*-1) -> 115019.34 | D28: =C28*rendimento_carteira -> 1150.1934
A29: 30 | B29: Quanto em 20 anos? | C29: =FV($C$13,$A28*12,$C$18*-1) -> 494627.68 | D29: =C29*rendimento_carteira -> 4946.2768
B30: Quanto em 30 anos? | C30: =FV($C$13,$A29*12,$C$18*-1) -> 1747482.1 | D30: =C30*rendimento_carteira -> 17474.821
B32: Perfil | D32: Conservador
B33: VALOR A SER INVESTIDO POR MÊS | D33: =aporte -> 500
B35: TIPO DE PERFIL | C35: Percentual Sugerido | D35: Valores
B36: PAPEL | C36: =VLOOKUP($D$32&"-"&B36,Planilha2!D:G,4,FALSE) -> 0.3 | D36: =$D$33*C36 -> 150
B37: TIJOLO | C37: =VLOOKUP($D$32&"-"&B37,Planilha2!D:G,4,FALSE) -> 0.5 | D37: =$D$33*C37 -> 250
B38: HÍBRIDOS | C38: =VLOOKUP($D$32&"-"&B38,Planilha2!D:G,4,FALSE) -> 0.1 | D38: =$D$33*C38 -> 50
B39: FOFs | C39: =VLOOKUP($D$32&"-"&B39,Planilha2!D:G,4,FALSE) -> 0.1 | D39: =$D$33*C39 -> 50
B40: DESENVOLVIMENTO | C40: =VLOOKUP($D$32&"-"&B40,Planilha2!D:G,4,FALSE) -> 0 | D40: =$D$33*C40 -> 0
B41: HOTELARIAS | C41: =VLOOKUP($D$32&"-"&B41,Planilha2!D:G,4,FALSE) -> 0 | D41: =$D$33*C41 -> 0

Sheet Planilha2
D8: CHAVE | E8: PERFIL | F8: TIPO DE FII | G8: %
D9: =E9&"-"&F9 -> Conservador-PAPEL | E9: Conservador | F9: PAPEL | G9: 0.3
D10: =E10&"-"&F10 -> Conservador-TIJOLO | E10: Conservador | F10: TIJOLO | G10: 0.5
D11: =E11&"-"&F11 -> Conservador-HÍBRIDOS | E11: Conservador | F11: HÍBRIDOS | G11: 0.1
D12: =E12&"-"&F12 -> Conservador-FOFs | E12: Conservador | F12: FOFs | G12: 0.1
D13: =E13&"-"&F13 -> Conservador-DESENVOLVIMENTO | E13: Conservador | F13: DESENVOLVIMENTO | G13: 0
D14: =E14&"-"&F14 -> Conservador-HOTELARIAS | E14: Conservador | F14: HOTELARIAS | G14: 0
D15: =E15&"-"&F15 -> Moderado-PAPEL | E15: Moderado | F15: PAPEL | G15: 0.32
D16: =E16&"-"&F16 -> Moderado-TIJOLO | E16: Moderado | F16: TIJOLO | G16: 0.4
D17: =E17&"-"&F17 -> Moderado-HÍBRIDOS | E17: Moderado | F17: HÍBRIDOS | G17: 0.08
D18: =E18&"-"&F18 -> Moderado-FOFs | E18: Moderado | F18: FOFs | G18: 0.1
D19: =E19&"-"&F19 -> Moderado-DESENVOLVIMENTO | E19: Moderado | F19: DESENVOLVIMENTO | G19: 0
D20: =E20&"-"&F20 -> Moderado-HOTELARIAS | E20: Moderado | F20: HOTELARIAS | G20: 0.1
... D26: =E26&"-"&F26 -> Agressivo-HOTELARIAS | E26: Agressivo | F26: HOTELARIAS | G26: 0.1
